aws_meun/__init__.py
aws_meun/cli.py
aws_meun/core.py
aws_meun-0.1.0a2.dist-info/LICENSE
aws_meun-0.1.0a2.dist-info/METADATA
aws_meun-0.1.0a2.dist-info/WHEEL
aws_meun-0.1.0a2.dist-info/entry_points.txt
aws_meun-0.1.0a2.dist-info/RECORD
