Metadata-Version: 2.1
Name: aws-meun
Version: 0.1.0a2
Summary: CLI tool to unsubscribe from AWS Marketing Emails
License: Unlicense
Author: wnkz
Author-email: wnkz@users.noreply.github.com
Requires-Python: >=3.8,<4.0
Classifier: License :: OSI Approved
Classifier: Programming Language :: Python :: 3
Classifier: Programming Language :: Python :: 3.8
Classifier: Programming Language :: Python :: 3.9
Classifier: Programming Language :: Python :: 3.10
Classifier: Programming Language :: Python :: 3.11
Classifier: Programming Language :: Python :: 3.12
Requires-Dist: httpx[http2] (>=0.26.0,<0.27.0)
